gpxcsv/__init__.py
gpxcsv/__main__.py
gpxcsv-0.3.1.dist-info/METADATA
gpxcsv-0.3.1.dist-info/WHEEL
gpxcsv-0.3.1.dist-info/entry_points.txt
gpxcsv-0.3.1.dist-info/licenses/LICENSE
gpxcsv-0.3.1.dist-info/RECORD
