Metadata-Version: 2.3
Name: gpxcsv
Version: 0.3.1
Summary: Convert Garmin GPX file to CSV or JSON
Project-URL: Documentation, https://github.com/astrowonk/gpxcsv/#readme
Project-URL: Issues, https://github.com/astrowonk/gpxcsv/issues
Project-URL: Source, https://github.com/astrowonk/gpxcsv
Author-email: Marcos Huerta <marcos@marcoshuerta.com>
License-Expression: MIT
License-File: LICENSE
Classifier: License :: OSI Approved :: MIT License
Classifier: Operating System :: OS Independent
Classifier: Programming Language :: Python
Classifier: Programming Language :: Python :: 3.7
Classifier: Programming Language :: Python :: 3.8
Classifier: Programming Language :: Python :: 3.9
Classifier: Programming Language :: Python :: 3.10
Classifier: Programming Language :: Python :: 3.11
Classifier: Programming Language :: Python :: 3.12
Classifier: Programming Language :: Python :: Implementation :: CPython
Classifier: Programming Language :: Python :: Implementation :: PyPy
Requires-Python: >=3.7
Requires-Dist: lxml
